privatereports/__init__.py
privatereports/privatereports.py
privatereports/templates/admin_privatereports.html
privatereports/templates/admin_privatereports_jinja.html
TracPrivateReports-1.3.0.dist-info/COPYING
TracPrivateReports-1.3.0.dist-info/METADATA
TracPrivateReports-1.3.0.dist-info/WHEEL
TracPrivateReports-1.3.0.dist-info/entry_points.txt
TracPrivateReports-1.3.0.dist-info/top_level.txt
TracPrivateReports-1.3.0.dist-info/zip-safe
TracPrivateReports-1.3.0.dist-info/RECORD
