Metadata-Version: 2.1
Name: TracPrivateReports
Version: 1.3.0
Summary: A trac plugin that lets you control which groups and
Home-page: https://trac-hacks.org/wiki/PrivateReportsPlugin
Author: Michael Henke
Author-email: michael.henke@she.net
License: BSD 3-Clause
Keywords: trac plugin security report group user
Platform: UNKNOWN
Classifier: Development Status :: 5 - Production/Stable
Classifier: Environment :: Plugins
Classifier: Environment :: Web Environment
Classifier: Framework :: Trac
Classifier: Intended Audience :: System Administrators
Classifier: License :: OSI Approved :: BSD License
Classifier: Natural Language :: English
Classifier: Operating System :: OS Independent
Classifier: Programming Language :: Python :: 2
Classifier: Programming Language :: Python :: 2.7
Classifier: Programming Language :: Python :: 3
Requires-Dist: Trac
